README.md
setup.py
agent_vn868/__init__.py
agent_vn868/__version__.py
agent_vn868/api.py
agent_vn868/exceptions.py
agent_vn868/parsers.py
agent_vn868/settings.py
agent_vn868/utils.py
cc_vn868.egg-info/PKG-INFO
cc_vn868.egg-info/SOURCES.txt
cc_vn868.egg-info/dependency_links.txt
cc_vn868.egg-info/not-zip-safe
cc_vn868.egg-info/requires.txt
cc_vn868.egg-info/top_level.txt