Metadata-Version: 2.1
Name: cc-vn868
Version: 1.0.0
Summary: cc-vn868 - vn868 Agent API
Home-page: https://cockreative.com/
Author: Cockroach Creative
Author-email: support@cockreative.com
License: Apache 2.0
Keywords: vn868
Platform: UNKNOWN
Classifier: Development Status :: 4 - Beta
Classifier: Intended Audience :: Developers
Classifier: Programming Language :: Python :: 3.7
Requires-Python: >=3.7.*
